DeepHME/DeepHME.py
DeepHME/ErrorProp.py
DeepHME/__init__.py
DeepHME/models/predict_quantiles3D_DL_v8/params_predict_quantiles3D_DL_v8_even.yaml
DeepHME/models/predict_quantiles3D_DL_v8/params_predict_quantiles3D_DL_v8_odd.yaml
DeepHME/models/predict_quantiles3D_DL_v8/predict_quantiles3D_DL_v8_even.onnx
DeepHME/models/predict_quantiles3D_DL_v8/predict_quantiles3D_DL_v8_odd.onnx
DeepHME/models/predict_quantiles3D_SL_v3/params_predict_quantiles3D_SL_v3_even.yaml
DeepHME/models/predict_quantiles3D_SL_v3/params_predict_quantiles3D_SL_v3_odd.yaml
DeepHME/models/predict_quantiles3D_SL_v3/predict_quantiles3D_SL_v3_even.onnx
DeepHME/models/predict_quantiles3D_SL_v3/predict_quantiles3D_SL_v3_odd.onnx
deephme-1.2.0.dist-info/METADATA
deephme-1.2.0.dist-info/WHEEL
deephme-1.2.0.dist-info/licenses/LICENSE
deephme-1.2.0.dist-info/RECORD
