Metadata-Version: 2.4
Name: DeepHME
Version: 1.2.0
Summary: Heavy Mass Estimator based on deep neural network
Project-URL: Homepage, https://github.com/cms-flaf/DeepHME
Author-email: abolshov <artem.e.bolshov@gmail.com>
License-Expression: MIT
License-File: LICENSE
Requires-Python: >=3.11
Requires-Dist: awkward>=2.8.5
Requires-Dist: numpy>=1.26.4
Requires-Dist: onnxruntime>=1.22.0
Requires-Dist: pandas>=2.3.1
Requires-Dist: pyyaml>=6.0.2
Requires-Dist: vector>=1.6.3
